np_audio_control-0.1.0.dist-info/METADATA
np_audio_control-0.1.0.dist-info/WHEEL
np_audio_control/__init__.py
np_audio_control/bases.py
np_audio_control/setvol.py
np_audio_control/utils.py
np_audio_control-0.1.0.dist-info/RECORD
